bitter/VERSION
bitter/__init__.py
bitter/cli.py
bitter/config.py
bitter/crawlers.py
bitter/models.py
bitter/utils.py
bitter/version.py
bitter/webserver.py
bitter/static/index.html
bitter/static/css/style.css
bitter/static/images/me.jpg
bitter/templates/base.html
bitter/templates/home.html
bitter/templates/limits.html
bitter/templates/sad.html
bitter/templates/thanks.html
bitter-0.9.4.dist-info/METADATA
bitter-0.9.4.dist-info/WHEEL
bitter-0.9.4.dist-info/entry_points.txt
bitter-0.9.4.dist-info/top_level.txt
bitter-0.9.4.dist-info/RECORD
