Metadata-Version: 2.1
Name: bitter
Version: 0.9.4
Summary: Simplifying how researchers access Data. It includes a CLI and a library.
Home-page: http://balkian.com
Author: J. Fernando Sanchez
Author-email: balkian@gmail.com
License: UNKNOWN
Platform: UNKNOWN
Classifier: Development Status :: 4 - Beta
Classifier: Intended Audience :: Developers
Classifier: Intended Audience :: Science/Research
Classifier: License :: OSI Approved :: Apache Software License
Classifier: Programming Language :: Python :: 2
Classifier: Programming Language :: Python :: 2.7
Classifier: Programming Language :: Python :: 3
Requires-Dist: sqlalchemy
Requires-Dist: twitter
Requires-Dist: click
Requires-Dist: tqdm
Requires-Dist: pyyaml
Provides-Extra: server
Requires-Dist: flask ; extra == 'server'
Requires-Dist: flask-oauthlib ; extra == 'server'
